MANIFEST.in
README.md
requirements.txt
setup.py
test-requirements.txt
supervisor_elastic/__init__.py
supervisor_elastic.egg-info/PKG-INFO
supervisor_elastic.egg-info/SOURCES.txt
supervisor_elastic.egg-info/dependency_links.txt
supervisor_elastic.egg-info/entry_points.txt
supervisor_elastic.egg-info/requires.txt
supervisor_elastic.egg-info/top_level.txt