Metadata-Version: 2.1
Name: supervisor-elastic
Version: 0.0.2
Summary: Stream supervisord logs to elastic via redis
Home-page: https://github.com/woutervb/supervisor_elastic
Author: Wouter van Bommel
Author-email: wouter@vanbommelonline.nl
License: GPLv2
Platform: UNKNOWN
Provides-Extra: tests
